{
 "allow_comments": 0,
 "allow_delete": 0,
 "allow_edit": 1,
 "allow_incomplete": 1,
 "allow_multiple": 0,
 "allow_print": 1,
 "anonymous": 0,
 "apply_document_permissions": 0,
 "banner_image": "",
 "button_label": "Submit",
 "condition_json": "[]",
 "creation": "2024-11-30 11:52:37.766611",
 "doc_type": "Recruitment Application",
 "docstatus": 0,
 "doctype": "Web Form",
 "idx": 0,
 "introduction_text": "<div class=\"ql-editor read-mode\"><p><strong>NOTE : </strong><span style=\"color: rgb(230, 0, 0);\">Any information given in this form that is not true will attract sanctions in accordance with the applicable laws.</span>\ufeff</p></div>",
 "is_standard": 1,
 "list_columns": [],
 "login_required": 1,
 "max_attachment_size": 0,
 "modified": "2025-06-27 18:51:56.205820",
 "modified_by": "Administrator",
 "module": "DRM",
 "name": "recruitment-application-form",
 "owner": "Administrator",
 "print_format": "RRI Print Format 2024",
 "published": 1,
 "route": "drm/recruitment-application-form",
 "show_attachments": 0,
 "show_list": 0,
 "show_sidebar": 0,
 "success_message": "Application saved successfully !",
 "success_title": "Saved",
 "success_url": "/drm/recruitment-application-form",
 "title": "Recruitment Application Form",
 "web_form_fields": [
  {
   "allow_read_on_all_link_options": 0,
   "fieldname": "nin_validation_section_section",
   "fieldtype": "Section Break",
   "hidden": 0,
   "label": "NIN Validation Section",
   "max_length": 0,
   "max_value": 0,
   "precision": "",
   "read_only": 0,
   "reqd": 0,
   "show_in_filter": 0
  },
  {
   "allow_read_on_all_link_options": 0,
   "default": "89RRI",
   "fieldname": "intake",
   "fieldtype": "Link",
   "hidden": 0,
   "label": "Intake",
   "max_length": 0,
   "max_value": 0,
   "options": "Regular Intake Application",
   "precision": "",
   "read_only": 1,
   "reqd": 0,
   "show_in_filter": 0
  },
  {
   "allow_read_on_all_link_options": 0,
   "depends_on": "eval: doc.trades_category != undefined",
   "fieldname": "date_of_birth",
   "fieldtype": "Date",
   "hidden": 0,
   "label": "Date of Birth",
   "max_length": 0,
   "max_value": 0,
   "precision": "",
   "read_only": 0,
   "reqd": 1,
   "show_in_filter": 0
  },
  {
   "allow_read_on_all_link_options": 0,
   "depends_on": "",
   "fieldname": "passport_photograph",
   "fieldtype": "HTML",
   "hidden": 0,
   "label": "Passport Photograph",
   "max_length": 0,
   "max_value": 0,
   "precision": "",
   "read_only": 0,
   "reqd": 0,
   "show_in_filter": 0
  },
  {
   "allow_read_on_all_link_options": 0,
   "fieldname": "passport_photograph_data",
   "fieldtype": "Text",
   "hidden": 0,
   "label": "Passport",
   "max_length": 0,
   "max_value": 0,
   "precision": "",
   "read_only": 1,
   "reqd": 0,
   "show_in_filter": 0
  },
  {
   "allow_read_on_all_link_options": 0,
   "fieldname": "column_break_wals",
   "fieldtype": "Column Break",
   "hidden": 0,
   "label": "",
   "max_length": 0,
   "max_value": 0,
   "precision": "",
   "read_only": 0,
   "reqd": 0,
   "show_in_filter": 0
  },
  {
   "allow_read_on_all_link_options": 0,
   "fieldname": "trades_category",
   "fieldtype": "Select",
   "hidden": 0,
   "label": "Trades Category",
   "max_length": 0,
   "max_value": 0,
   "options": "Non-Trades\nTrades",
   "precision": "",
   "read_only": 0,
   "reqd": 1,
   "show_in_filter": 0
  },
  {
   "allow_read_on_all_link_options": 0,
   "fieldname": "applicant_nin",
   "fieldtype": "Data",
   "hidden": 0,
   "label": "Applicant NIN",
   "max_length": 0,
   "max_value": 0,
   "precision": "",
   "read_only": 0,
   "reqd": 1,
   "show_in_filter": 0
  },
  {
   "allow_read_on_all_link_options": 0,
   "default": "",
   "depends_on": "eval:doc.surname !== undefined",
   "fieldname": "surname",
   "fieldtype": "Data",
   "hidden": 0,
   "label": "Surname",
   "max_length": 0,
   "max_value": 0,
   "precision": "",
   "read_only": 1,
   "reqd": 1,
   "show_in_filter": 0
  },
  {
   "allow_read_on_all_link_options": 0,
   "default": "",
   "depends_on": "eval:doc.first_name !== undefined",
   "fieldname": "first_name",
   "fieldtype": "Data",
   "hidden": 0,
   "label": "First Name",
   "max_length": 0,
   "max_value": 0,
   "precision": "",
   "read_only": 1,
   "reqd": 1,
   "show_in_filter": 0
  },
  {
   "allow_read_on_all_link_options": 0,
   "depends_on": "eval:doc.other_name !== undefined",
   "fieldname": "other_names",
   "fieldtype": "Data",
   "hidden": 0,
   "label": "Other Names",
   "max_length": 0,
   "max_value": 0,
   "precision": "",
   "read_only": 1,
   "reqd": 0,
   "show_in_filter": 0
  },
  {
   "allow_read_on_all_link_options": 0,
   "fieldname": "personal_details_tab",
   "fieldtype": "Page Break",
   "hidden": 0,
   "label": "Personal Details",
   "max_length": 0,
   "max_value": 0,
   "precision": "",
   "read_only": 0,
   "reqd": 0,
   "show_in_filter": 0
  },
  {
   "allow_read_on_all_link_options": 0,
   "fieldname": "state",
   "fieldtype": "Link",
   "hidden": 0,
   "label": "State",
   "max_length": 0,
   "max_value": 0,
   "options": "State",
   "precision": "",
   "read_only": 0,
   "reqd": 1,
   "show_in_filter": 0
  },
  {
   "allow_read_on_all_link_options": 0,
   "fieldname": "state_code",
   "fieldtype": "Data",
   "hidden": 0,
   "label": "State Code",
   "max_length": 0,
   "max_value": 0,
   "precision": "",
   "read_only": 1,
   "reqd": 1,
   "show_in_filter": 0
  },
  {
   "allow_read_on_all_link_options": 0,
   "depends_on": "eval: doc.state != undefined",
   "fieldname": "local_government",
   "fieldtype": "Select",
   "hidden": 0,
   "label": "Local Government",
   "max_length": 0,
   "max_value": 0,
   "options": "",
   "precision": "",
   "read_only": 0,
   "reqd": 1,
   "show_in_filter": 0
  },
  {
   "allow_read_on_all_link_options": 0,
   "fieldname": "religion",
   "fieldtype": "Select",
   "hidden": 0,
   "label": "Religion",
   "max_length": 0,
   "max_value": 0,
   "options": "Christianity\nIslam",
   "precision": "",
   "read_only": 0,
   "reqd": 1,
   "show_in_filter": 0
  },
  {
   "allow_read_on_all_link_options": 0,
   "fieldname": "marital_status",
   "fieldtype": "Select",
   "hidden": 0,
   "label": "Marital Status",
   "max_length": 0,
   "max_value": 0,
   "options": "Single\nMarried\nWidowed\nSeparated\nDivorced",
   "precision": "",
   "read_only": 0,
   "reqd": 1,
   "show_in_filter": 0
  },
  {
   "allow_read_on_all_link_options": 0,
   "fieldname": "column_break_bico",
   "fieldtype": "Column Break",
   "hidden": 0,
   "label": "",
   "max_length": 0,
   "max_value": 0,
   "precision": "",
   "read_only": 0,
   "reqd": 0,
   "show_in_filter": 0
  },
  {
   "allow_read_on_all_link_options": 0,
   "fieldname": "gender",
   "fieldtype": "Select",
   "hidden": 0,
   "label": "Gender",
   "max_length": 0,
   "max_value": 0,
   "options": "Male\nFemale",
   "precision": "",
   "read_only": 0,
   "reqd": 1,
   "show_in_filter": 0
  },
  {
   "allow_read_on_all_link_options": 0,
   "fieldname": "age",
   "fieldtype": "Data",
   "hidden": 0,
   "label": "Age",
   "max_length": 0,
   "max_value": 0,
   "precision": "",
   "read_only": 0,
   "reqd": 0,
   "show_in_filter": 0
  },
  {
   "allow_read_on_all_link_options": 0,
   "fieldname": "height",
   "fieldtype": "Float",
   "hidden": 0,
   "label": "Height (cm)",
   "max_length": 0,
   "max_value": 0,
   "precision": "2",
   "read_only": 0,
   "reqd": 1,
   "show_in_filter": 0
  },
  {
   "allow_read_on_all_link_options": 0,
   "fieldname": "weight",
   "fieldtype": "Int",
   "hidden": 0,
   "label": "Weight (kg)",
   "max_length": 0,
   "max_value": 0,
   "precision": "",
   "read_only": 0,
   "reqd": 1,
   "show_in_filter": 0
  },
  {
   "allow_read_on_all_link_options": 0,
   "fieldname": "contact_details_tab",
   "fieldtype": "Page Break",
   "hidden": 0,
   "label": "Contact Details",
   "max_length": 0,
   "max_value": 0,
   "precision": "",
   "read_only": 0,
   "reqd": 0,
   "show_in_filter": 0
  },
  {
   "allow_read_on_all_link_options": 0,
   "fieldname": "mobile_number",
   "fieldtype": "Data",
   "hidden": 0,
   "label": "Mobile Number",
   "max_length": 0,
   "max_value": 0,
   "precision": "",
   "read_only": 0,
   "reqd": 0,
   "show_in_filter": 0
  },
  {
   "allow_read_on_all_link_options": 0,
   "fieldname": "contact_address",
   "fieldtype": "Small Text",
   "hidden": 0,
   "label": "Contact Address",
   "max_length": 0,
   "max_value": 0,
   "precision": "",
   "read_only": 0,
   "reqd": 1,
   "show_in_filter": 0
  },
  {
   "allow_read_on_all_link_options": 0,
   "fieldname": "nok_name",
   "fieldtype": "Data",
   "hidden": 0,
   "label": "NOK Name",
   "max_length": 0,
   "max_value": 0,
   "precision": "",
   "read_only": 0,
   "reqd": 1,
   "show_in_filter": 0
  },
  {
   "allow_read_on_all_link_options": 0,
   "fieldname": "nok_relationship",
   "fieldtype": "Select",
   "hidden": 0,
   "label": "NOK Relationship",
   "max_length": 0,
   "max_value": 0,
   "options": "Mother\nFather\nBrother\nSister\nGuardian",
   "precision": "",
   "read_only": 0,
   "reqd": 1,
   "show_in_filter": 0
  },
  {
   "allow_read_on_all_link_options": 0,
   "fieldname": "nok_phone_number",
   "fieldtype": "Data",
   "hidden": 0,
   "label": "NOK Phone Number",
   "max_length": 0,
   "max_value": 0,
   "precision": "",
   "read_only": 0,
   "reqd": 1,
   "show_in_filter": 0
  },
  {
   "allow_read_on_all_link_options": 0,
   "fieldname": "column_break_wtvg",
   "fieldtype": "Column Break",
   "hidden": 0,
   "label": "",
   "max_length": 0,
   "max_value": 0,
   "precision": "",
   "read_only": 0,
   "reqd": 0,
   "show_in_filter": 0
  },
  {
   "allow_read_on_all_link_options": 0,
   "fieldname": "email_address",
   "fieldtype": "Data",
   "hidden": 0,
   "label": "Email Address",
   "max_length": 0,
   "max_value": 0,
   "precision": "",
   "read_only": 1,
   "reqd": 1,
   "show_in_filter": 0
  },
  {
   "allow_read_on_all_link_options": 0,
   "fieldname": "permanent_address",
   "fieldtype": "Small Text",
   "hidden": 0,
   "label": "Permanent Address",
   "max_length": 0,
   "max_value": 0,
   "precision": "",
   "read_only": 0,
   "reqd": 1,
   "show_in_filter": 0
  },
  {
   "allow_read_on_all_link_options": 0,
   "fieldname": "nok_address",
   "fieldtype": "Small Text",
   "hidden": 0,
   "label": "NOK Address",
   "max_length": 0,
   "max_value": 0,
   "precision": "",
   "read_only": 0,
   "reqd": 1,
   "show_in_filter": 0
  },
  {
   "allow_read_on_all_link_options": 0,
   "fieldname": "education_details_tab",
   "fieldtype": "Page Break",
   "hidden": 0,
   "label": "Education Details",
   "max_length": 0,
   "max_value": 0,
   "precision": "",
   "read_only": 0,
   "reqd": 0,
   "show_in_filter": 0
  },
  {
   "allow_read_on_all_link_options": 0,
   "fieldname": "primary_school_name",
   "fieldtype": "Data",
   "hidden": 0,
   "label": "Primary School Name",
   "max_length": 0,
   "max_value": 0,
   "precision": "",
   "read_only": 0,
   "reqd": 1,
   "show_in_filter": 0
  },
  {
   "allow_read_on_all_link_options": 0,
   "fieldname": "primary_school_period",
   "fieldtype": "Data",
   "hidden": 0,
   "label": "Primary School Period",
   "max_length": 0,
   "max_value": 0,
   "precision": "",
   "read_only": 0,
   "reqd": 1,
   "show_in_filter": 0
  },
  {
   "allow_read_on_all_link_options": 0,
   "fieldname": "column_break_qnjl",
   "fieldtype": "Column Break",
   "hidden": 0,
   "label": "",
   "max_length": 0,
   "max_value": 0,
   "precision": "",
   "read_only": 0,
   "reqd": 0,
   "show_in_filter": 0
  },
  {
   "allow_read_on_all_link_options": 0,
   "fieldname": "secondary_school_name",
   "fieldtype": "Data",
   "hidden": 0,
   "label": "Secondary School Name",
   "max_length": 0,
   "max_value": 0,
   "precision": "",
   "read_only": 0,
   "reqd": 1,
   "show_in_filter": 0
  },
  {
   "allow_read_on_all_link_options": 0,
   "fieldname": "secondary_school_period",
   "fieldtype": "Data",
   "hidden": 0,
   "label": "Secondary School Period",
   "max_length": 0,
   "max_value": 0,
   "precision": "",
   "read_only": 0,
   "reqd": 1,
   "show_in_filter": 0
  },
  {
   "allow_read_on_all_link_options": 0,
   "fieldname": "section_break_lxfz",
   "fieldtype": "Section Break",
   "hidden": 0,
   "label": "",
   "max_length": 0,
   "max_value": 0,
   "precision": "",
   "read_only": 0,
   "reqd": 0,
   "show_in_filter": 0
  },
  {
   "allow_read_on_all_link_options": 0,
   "fieldname": "secondary_school_grades",
   "fieldtype": "Table",
   "hidden": 1,
   "label": "Secondary School Grades",
   "max_length": 0,
   "max_value": 0,
   "options": "Subject Grade",
   "precision": "",
   "read_only": 0,
   "reqd": 0,
   "show_in_filter": 0
  },
  {
   "allow_read_on_all_link_options": 0,
   "fieldname": "documents__addtional_information_tab",
   "fieldtype": "Page Break",
   "hidden": 0,
   "label": "Documents / Addtional Information",
   "max_length": 0,
   "max_value": 0,
   "precision": "",
   "read_only": 0,
   "reqd": 0,
   "show_in_filter": 0
  },
  {
   "allow_read_on_all_link_options": 0,
   "fieldname": "primary_school_certificate",
   "fieldtype": "Attach",
   "hidden": 0,
   "label": "Primary School Certificate",
   "max_length": 0,
   "max_value": 0,
   "precision": "",
   "read_only": 0,
   "reqd": 1,
   "show_in_filter": 0
  },
  {
   "allow_read_on_all_link_options": 0,
   "fieldname": "secondary_school_certificate",
   "fieldtype": "Attach",
   "hidden": 0,
   "label": "Secondary School Certificate",
   "max_length": 0,
   "max_value": 0,
   "precision": "",
   "read_only": 0,
   "reqd": 1,
   "show_in_filter": 0
  },
  {
   "allow_read_on_all_link_options": 0,
   "depends_on": "eval: doc.trades_category == 'Trades'",
   "fieldname": "trade_test_certificate",
   "fieldtype": "Attach",
   "hidden": 0,
   "label": "Trade Test Certificate",
   "max_length": 0,
   "max_value": 0,
   "precision": "",
   "read_only": 0,
   "reqd": 0,
   "show_in_filter": 0
  },
  {
   "allow_read_on_all_link_options": 0,
   "fieldname": "column_break_qiqq",
   "fieldtype": "Column Break",
   "hidden": 0,
   "label": "",
   "max_length": 0,
   "max_value": 0,
   "precision": "",
   "read_only": 0,
   "reqd": 0,
   "show_in_filter": 0
  },
  {
   "allow_read_on_all_link_options": 0,
   "fieldname": "birth_certificate",
   "fieldtype": "Attach",
   "hidden": 0,
   "label": "Birth Certificate",
   "max_length": 0,
   "max_value": 0,
   "precision": "",
   "read_only": 0,
   "reqd": 1,
   "show_in_filter": 0
  },
  {
   "allow_read_on_all_link_options": 0,
   "fieldname": "certificate_of_origin",
   "fieldtype": "Attach",
   "hidden": 0,
   "label": "Certificate of Origin",
   "max_length": 0,
   "max_value": 0,
   "precision": "",
   "read_only": 0,
   "reqd": 1,
   "show_in_filter": 0
  },
  {
   "allow_read_on_all_link_options": 0,
   "fieldname": "additional_information_section",
   "fieldtype": "Section Break",
   "hidden": 0,
   "label": "Additional Information",
   "max_length": 0,
   "max_value": 0,
   "precision": "",
   "read_only": 0,
   "reqd": 0,
   "show_in_filter": 0
  },
  {
   "allow_read_on_all_link_options": 0,
   "fieldname": "afn_service",
   "fieldtype": "Select",
   "hidden": 0,
   "label": "Have you ever served in the Armed Forces of Nigeria?",
   "max_length": 0,
   "max_value": 0,
   "options": "No\nYes",
   "precision": "",
   "read_only": 0,
   "reqd": 1,
   "show_in_filter": 0
  },
  {
   "allow_read_on_all_link_options": 0,
   "fieldname": "have_you_ever_been_convicted",
   "fieldtype": "Select",
   "hidden": 0,
   "label": "Have you ever been convicted?",
   "max_length": 0,
   "max_value": 0,
   "options": "Yes\nNo",
   "precision": "",
   "read_only": 0,
   "reqd": 1,
   "show_in_filter": 0
  },
  {
   "allow_read_on_all_link_options": 0,
   "fieldname": "detained",
   "fieldtype": "Select",
   "hidden": 0,
   "label": "Have you ever been detained by the police?",
   "max_length": 0,
   "max_value": 0,
   "options": "Yes\nNo",
   "precision": "",
   "read_only": 0,
   "reqd": 1,
   "show_in_filter": 0
  },
  {
   "allow_read_on_all_link_options": 0,
   "default": "0",
   "description": "Confirm that all information entered are correct to the best of your knowledge.",
   "fieldname": "declaration",
   "fieldtype": "Check",
   "hidden": 0,
   "label": "Declaration",
   "max_length": 0,
   "max_value": 0,
   "precision": "",
   "read_only": 0,
   "reqd": 1,
   "show_in_filter": 0
  },
  {
   "allow_read_on_all_link_options": 0,
   "fieldname": "column_break_mgfk",
   "fieldtype": "Column Break",
   "hidden": 0,
   "label": "",
   "max_length": 0,
   "max_value": 0,
   "precision": "",
   "read_only": 0,
   "reqd": 0,
   "show_in_filter": 0
  },
  {
   "allow_read_on_all_link_options": 0,
   "fieldname": "oversea_travel",
   "fieldtype": "Select",
   "hidden": 0,
   "label": "Overseas Travel?",
   "max_length": 0,
   "max_value": 0,
   "options": "No\nYes",
   "precision": "",
   "read_only": 0,
   "reqd": 0,
   "show_in_filter": 0
  },
  {
   "allow_read_on_all_link_options": 0,
   "depends_on": "eval: doc.overseas_travel == 'Yes'",
   "fieldname": "countries_visited",
   "fieldtype": "Small Text",
   "hidden": 0,
   "label": "Countries Visited",
   "max_length": 0,
   "max_value": 0,
   "precision": "",
   "read_only": 0,
   "reqd": 0,
   "show_in_filter": 0
  }
 ]
}